Metadata-Version: 2.1
Name: lego-image-converter
Version: 0.1.1
Summary: First minor update after formal release
Home-page: https://github.com/zl3311/lego_image_converter
Author: Zequn Li
Author-email: zequn1992@gmail.com
License: MIT
Download-URL: https://github.com/zl3311/lego_image_converter/archive/refs/tags/0.1.1.tar.gz
Keywords: pypi,lego_image_converter,lego,image,8bit,art
Platform: UNKNOWN
Classifier: Intended Audience :: Developers
Classifier: Topic :: Software Development :: Documentation
Classifier: License :: OSI Approved :: MIT License
Classifier: Programming Language :: Python :: 3
License-File: LICENSE
